_tskit.cpython-311-darwin.so
tskit/__init__.py
tskit/__main__.py
tskit/_version.py
tskit/cli.py
tskit/combinatorics.py
tskit/drawing.py
tskit/exceptions.py
tskit/genotypes.py
tskit/intervals.py
tskit/metadata.py
tskit/provenance.py
tskit/provenance.schema.json
tskit/stats.py
tskit/tables.py
tskit/text_formats.py
tskit/trees.py
tskit/util.py
tskit/vcf.py
tskit-0.6.4.dist-info/licenses/LICENSE
tskit-0.6.4.dist-info/METADATA
tskit-0.6.4.dist-info/WHEEL
tskit-0.6.4.dist-info/entry_points.txt
tskit-0.6.4.dist-info/top_level.txt
tskit-0.6.4.dist-info/RECORD
